langllm/__init__.py
langllm/llm_api/__init__.py
langllm/llm_api/llm_client.py
langllm/llm_api/llm_client_chat_model.py
langllm/llm_api/message_chunk.py
langllm/llm_api/thinking_config.py
langllm/utils/__init__.py
langllm/utils/schema_parse.py
langllm-0.1.0.dist-info/licenses/LICENSE
langllm-0.1.0.dist-info/METADATA
langllm-0.1.0.dist-info/WHEEL
langllm-0.1.0.dist-info/top_level.txt
langllm-0.1.0.dist-info/RECORD
