Metadata-Version: 2.4
Name: LangLLM
Version: 0.1.0
Summary: LangChain-compatible LLM agent framework with Chain-of-Thought and structured output support
Author: Cassian
License: MIT License
Classifier: Development Status :: 4 - Beta
Classifier: Intended Audience :: Developers
Classifier: Intended Audience :: Science/Research
Classifier: Programming Language :: Python :: 3
Classifier: License :: OSI Approved :: MIT License
Classifier: Operating System :: OS Independent
Classifier: Topic :: Scientific/Engineering :: Artificial Intelligence
Requires-Python: >=3.8
License-File: LICENSE
Requires-Dist: langchain-core>=0.2.0
Requires-Dist: openai>=1.0.0
Requires-Dist: pydantic>=2.0.0
Dynamic: license-file
